MANIFEST.in
README.md
requirements.txt
setup.py
django_shipping.egg-info/PKG-INFO
django_shipping.egg-info/SOURCES.txt
django_shipping.egg-info/dependency_links.txt
django_shipping.egg-info/requires.txt
django_shipping.egg-info/top_level.txt
shipping/__init__.py
shipping/__init__.pyc
shipping/admin.py
shipping/admin.pyc
shipping/models.py
shipping/models.pyc
shipping/urls.py
shipping/urls.pyc
shipping/views.py
shipping/views.pyc
shipping/carriers/__init__.py
shipping/carriers/__init__.pyc
shipping/carriers/correios.py
shipping/carriers/correios.pyc
shipping/carriers/upsinterface.py
shipping/carriers/upsinterface.pyc
shipping/migrations/0001_initial.py
shipping/migrations/0001_initial.pyc
shipping/migrations/0002_insert_zone_country_state.py
shipping/migrations/0002_insert_zone_country_state.pyc
shipping/migrations/0003_insert_carriers.py
shipping/migrations/0003_insert_carriers.pyc
shipping/migrations/0004_auto__add_field_upscarrier_currency_code.py
shipping/migrations/0004_auto__add_field_upscarrier_currency_code.pyc
shipping/migrations/0005_auto__add_field_correioscarrier_esedex_code.py
shipping/migrations/__init__.py
shipping/migrations/__init__.pyc
shipping/migrations/country.sql
shipping/migrations/state.sql
shipping/migrations/zone.sql
shipping/packing/__init__.py
shipping/packing/__init__.pyc
shipping/packing/package.py
shipping/packing/package.pyc
shipping/static/shipping/css/shipping.css
shipping/static/shipping/img/loading.gif
shipping/static/shipping/js/shipping.freight.js
shipping/templates/shipping/freight.html
shipping/templatetags/__init__.py
shipping/templatetags/shipping_extras.py