Metadata-Version: 1.0
Name: django-shipping
Version: 0.0.8
Summary: Django shipping tool
Home-page: http://github.com/quatix/django-shipping
Author: Marcel Nicolay
Author-email: marcelnicolay@gmail.com
License: UNKNOWN
Platform: UNKNOWN
